{
  "estaciones": [
    {
      "nombre": "La Plata",
      "altura": 1.37,
      "fechaHora": "14:10",
      "tendencia": "BAJANDO",
      "vientoActual": null,
      "vientoDireccion": "S/D",
      "fechaHoraViento": "",
      "historialAltura": [
        {
          "hora": "12:40",
          "valor": 1.45
        },
        {
          "hora": "12:50",
          "valor": 1.45
        },
        {
          "hora": "13:00",
          "valor": 1.44
        },
        {
          "hora": "13:10",
          "valor": 1.44
        },
        {
          "hora": "13:20",
          "valor": 1.42
        },
        {
          "hora": "13:30",
          "valor": 1.42
        },
        {
          "hora": "13:40",
          "valor": 1.41
        },
        {
          "hora": "13:50",
          "valor": 1.4
        },
        {
          "hora": "14:00",
          "valor": 1.39
        },
        {
          "hora": "14:10",
          "valor": 1.37
        }
      ],
      "historialViento": []
    }
  ]
}